[
    {
      "id": 1,
      "Title": "F1Tenth Autonomous RC Car",
      "Blurb":
        "Train and test an open source competition autonomous racecar in ROS2 using a camera, lidar and machine learning",
      "Link:":"https://github.com/Binghamton-University-Roboracer",
      "Image": "autonomous-car.jpg",
      "Languages": ["Python", "Bash", "C++"]
    },
    {
        "id": 2,
      "Title": "FPGA VHDL & Embedded C Metal Detector",
      "Blurb":
        "Programmed a battery powered fpga system with a softcore processor to detect magnetic field strength using a coil and a 7-segment display",
      "Image": "fpga.png",
      "Link": "",
      "Languages": ["VHDL","Embedded C"]
    },
    {
        "id": 3,
      "Title": "Portfolio Website",
      "Blurb":
        "Website designed to introduce myself and show off some recent projects. Created with React.js & hosted on Github Pages",
      "Link" : "https://github.com/c3hodgins/portfolio",
      "Image": "vite-react.png",
      "Languages": ["Javascript","React.js"]
    }
]